conflict/__init__.py
conflict/module_print.py
conflictyaroslav2131234-0.2.0.dist-info/METADATA
conflictyaroslav2131234-0.2.0.dist-info/WHEEL
conflictyaroslav2131234-0.2.0.dist-info/top_level.txt
conflictyaroslav2131234-0.2.0.dist-info/RECORD
