Metadata-Version: 2.1
Name: conflictyaroslav2131234
Version: 0.2.0
Summary: A conflict Python package
Home-page: UNKNOWN
Author: Yaroslav Yaroslav
License: UNKNOWN
Platform: UNKNOWN
Requires-Dist: numpy (>=1.21.0)
